content_type_editor/__init__.py
content_type_editor/__main__.py
content_type_editor/asciidoc.py
content_type_editor/cli.py
content_type_editor/webui.py
content_type_editor-0.9.6.dist-info/licenses/LICENSE
content_type_editor-0.9.6.dist-info/METADATA
content_type_editor-0.9.6.dist-info/WHEEL
content_type_editor-0.9.6.dist-info/entry_points.txt
content_type_editor-0.9.6.dist-info/top_level.txt
content_type_editor-0.9.6.dist-info/RECORD
