Metadata-Version: 2.4
Name: content-type-editor
Version: 0.9.6
Summary: Add the content type attribute to AsciiDoc files.
Author-email: Jaromir Hradilek <jhradilek@gmail.com>
License-Expression: MIT
Project-URL: Homepage, https://github.com/jhradilek/content-type-editor
Project-URL: Repository, https://github.com/jhradilek/content-type-editor
Project-URL: Issues, https://github.com/jhradilek/content-type-editor/issues
Classifier: Programming Language :: Python :: 3
Classifier: Operating System :: OS Independent
Classifier: Development Status :: 5 - Production/Stable
Classifier: Environment :: Web Environment
Classifier: Intended Audience :: End Users/Desktop
Classifier: Topic :: Documentation
Requires-Python: >=3.10
License-File: LICENSE
Requires-Dist: streamlit>=1.45.0
Dynamic: license-file
